passwordInput/__init__.py
passwordInput/passwordInput.py
passwordInput-1.1.dist-info/METADATA
passwordInput-1.1.dist-info/WHEEL
passwordInput-1.1.dist-info/top_level.txt
passwordInput-1.1.dist-info/RECORD
