Metadata-Version: 2.1
Name: passwordInput
Version: 1.1
Summary: Password input for python.
Home-page: https://github.com/MAMOSKO/python-password-input
Author: MAMOSKO
Author-email: admin@mamoskomail.ml
License: UNKNOWN
Project-URL: Bug Tracker, https://github.com/MAMOSKO/python-password-input/issues
Platform: UNKNOWN
Classifier: Programming Language :: Python :: 3
Classifier: License :: OSI Approved :: MIT License
Classifier: Operating System :: OS Independent
Requires-Python: >=3.6
